MultiscaleEMD/__init__.py
MultiscaleEMD/convolutional_sinkhorn.py
MultiscaleEMD/dataset.py
MultiscaleEMD/diffusion_emd.py
MultiscaleEMD/emd.py
MultiscaleEMD/estimate_utils.py
MultiscaleEMD/metric_tree.py
MultiscaleEMD/tree.py
MultiscaleEMD/version.py
MultiscaleEMD-1.1.1.dist-info/LICENSE
MultiscaleEMD-1.1.1.dist-info/METADATA
MultiscaleEMD-1.1.1.dist-info/WHEEL
MultiscaleEMD-1.1.1.dist-info/top_level.txt
MultiscaleEMD-1.1.1.dist-info/RECORD
