Metadata-Version: 2.1
Name: MultiscaleEMD
Version: 1.1.1
Summary: Multiscale approximations to the earth mover's distance.
Home-page: https://github.com/atong01/MultiscaleEMD
Author: Alexander Tong
Author-email: alexandertongdev@gmail.com
License: MIT
License-File: LICENSE
Requires-Dist: numpy (>=1.16.0)
Requires-Dist: scipy
Requires-Dist: matplotlib (>=3.0)
Requires-Dist: pot
Requires-Dist: pygsp
Requires-Dist: graphtools
Requires-Dist: scikit-learn (>=1.0.0)
Provides-Extra: doc
Requires-Dist: sphinx ; extra == 'doc'
Requires-Dist: sphinxcontrib-napoleon ; extra == 'doc'
Requires-Dist: ipykernel ; extra == 'doc'
Requires-Dist: nbsphinx ; extra == 'doc'
Requires-Dist: autodocsumm ; extra == 'doc'
Provides-Extra: test
Requires-Dist: pandas ; extra == 'test'
Requires-Dist: black ; extra == 'test'
Requires-Dist: flake8 ; extra == 'test'
Requires-Dist: pytest ; extra == 'test'
